ndn/__init__.py
ndn/storage/__init__.py
ndn/storage/disk.py
ndn/storage/leveldb.py
ndn/storage/memory.py
ndn/storage/mongodb.py
ndn/storage/sqlite.py
ndn/storage/storage.py
ndn_storage-0.2.3.dist-info/AUTHORS.rst
ndn_storage-0.2.3.dist-info/LICENSE.rst
ndn_storage-0.2.3.dist-info/METADATA
ndn_storage-0.2.3.dist-info/WHEEL
ndn_storage-0.2.3.dist-info/top_level.txt
ndn_storage-0.2.3.dist-info/RECORD
