Metadata-Version: 2.1
Name: ndn-storage
Version: 0.2.3
Summary: An NDN Storage Library for Applications in Python 3
Home-page: https://github.com/justincpresley/ndn-python-storage
Download-URL: https://pypi.python.org/pypi/ndn-storage
Author: Justin C Presley
Author-email: justincpresley@gmail.com
Maintainer: Justin C Presley
Maintainer-email: justincpresley@gmail.com
License: Apache License 2.0
Project-URL: Bug Tracker, https://github.com/justincpresley/ndn-python-storage/issues
Project-URL: Source Code, https://github.com/justincpresley/ndn-python-storage
Keywords: NDN STORAGE DISK MEMORY CACHE
Platform: UNKNOWN
Classifier: Development Status :: 4 - Beta
Classifier: Intended Audience :: Developers
Classifier: Topic :: Software Development :: Libraries
Classifier: Topic :: Internet
Classifier: Topic :: System :: Networking
Classifier: License :: OSI Approved :: Apache Software License
Classifier: Programming Language :: Python :: 3.8
Classifier: Programming Language :: Python :: 3.9
Classifier: Programming Language :: Python :: 3.10
Requires-Python: >=3.8
License-File: LICENSE.rst
License-File: AUTHORS.rst
Requires-Dist: plyvel (>=1.4.0)
Requires-Dist: pymongo (>=4.0.1)
Requires-Dist: python-ndn (>=0.3)
